{
    "name": "Предмети загарбників",
    "icon": "minecraft:ender_chest",
    "category": "apotheosis:adventure/mobs",
	"flag": "apotheosis:adventure",
	"sortnum": 2,
    "pages": [
        {
            "type": "patchouli:text",
            "text": "Кожен загарбник має лише один афіксний предмет, а також поаністю зачароване спорядження.$(p)Цей афіксний предмет гарантовано випадатиме після смерті та матиме таку ж рідкість, як і загарбник.$(p)Афікси на ньому, як правило, сильніші, ніж зазвичай."
        },
		{
			"type": "patchouli:text",
			"text": "Цей предмет сам по собі є трофеєм, який ви отримаєте, вбивши загарбника, і він, ймовірно, того вартий.$(p)Як пам'ятка про початкового власника, кожен предмет матиме ім'я загарбника перед назвою предмета."
		}
	]
}